minjiang_host_client/__init__.py
minjiang_host_client/direct_group.cp311-win_amd64.pyd
minjiang_host_client/direct_group.pyi
minjiang_host_client/base/__init__.py
minjiang_host_client/base/channel.cp311-win_amd64.pyd
minjiang_host_client/base/channel.pyi
minjiang_host_client/base/monitor.cp311-win_amd64.pyd
minjiang_host_client/base/monitor.pyi
minjiang_host_client/base/server.cp311-win_amd64.pyd
minjiang_host_client/base/server.pyi
minjiang_host_client/base/worker.cp311-win_amd64.pyd
minjiang_host_client/base/worker.pyi
minjiang_host_client/base/worker_monitors.cp311-win_amd64.pyd
minjiang_host_client/base/worker_monitors.pyi
minjiang_host_client/server/__init__.py
minjiang_host_client/server/direct_link.cp311-win_amd64.pyd
minjiang_host_client/server/direct_link.pyi
minjiang_host_client/server/final.cp311-win_amd64.pyd
minjiang_host_client/server/final.pyi
minjiang_host_client/server/main.cp311-win_amd64.pyd
minjiang_host_client/server/main.pyi
minjiang_host_client/server/result.cp311-win_amd64.pyd
minjiang_host_client/server/result.pyi
minjiang_host_client/server/tasks.cp311-win_amd64.pyd
minjiang_host_client/server/tasks.pyi
minjiang_host_client/server/waveform.cp311-win_amd64.pyd
minjiang_host_client/server/waveform.pyi
minjiang_host_client/server/worker_monitor.cp311-win_amd64.pyd
minjiang_host_client/server/worker_monitor.pyi
minjiang_host_client/utils/__init__.py
minjiang_host_client/utils/database.cp311-win_amd64.pyd
minjiang_host_client/utils/database.pyi
minjiang_host_client/utils/device.cp311-win_amd64.pyd
minjiang_host_client/utils/device.pyi
minjiang_host_client/utils/device_manager.cp311-win_amd64.pyd
minjiang_host_client/utils/device_manager.pyi
minjiang_host_client/utils/direct_link.cp311-win_amd64.pyd
minjiang_host_client/utils/direct_link.pyi
minjiang_host_client/utils/get_html.cp311-win_amd64.pyd
minjiang_host_client/utils/get_html.pyi
minjiang_host_client/utils/local.cp311-win_amd64.pyd
minjiang_host_client/utils/local.pyi
minjiang_host_client-0.3.12.dist-info/METADATA
minjiang_host_client-0.3.12.dist-info/WHEEL
minjiang_host_client-0.3.12.dist-info/top_level.txt
minjiang_host_client-0.3.12.dist-info/RECORD
